Workbook

Sheet 校准摘要
B1: 结论：10 个案例均已生成完整报告并通过本轮静态结构与规则复核；结果为同会话自评，不是独立盲测准确率，也不涉及模型权重训练。
B2: 金融产品照妖镜｜十案例校准摘要
B5: 案例总数 | E5: 完整报告数 | H5: 结构验收通过
B6: =COUNTA('案例结果'!A4:A13) | E6: =COUNTA('完整报告'!A4:A13) | H6: =COUNTIF('案例结果'!R4:R13,"通过")
B7: 规则复核通过（自评） | E7: 硬性触发案例 | H7: 对照案例等级
B8: =COUNTIF('案例结果'!S4:S13,"通过") | E8: =COUNTIF('案例结果'!L4:L13,"是") | H8: ='案例结果'!M13
B10: 风险等级分布 | E10: 复现与解释边界
B11: 等级 | C11: 案例数 | E11: 方法：每次只使用一个案例输入，按六步工作流生成报告，输出后再对照预期触发点。
B12: 低 | C12: =COUNTIF('案例结果'!M4:M13,B12) | E12: 记录：保留 A—E 分数、总分、硬性触发、信息完整度、证据、人工复核和完整报告。
B13: 中 | C13: =COUNTIF('案例结果'!M4:M13,B13) | E13: 验收：八个报告模块、评分拆解与边界声明均做静态检查；预期规则由本轮输出后复核。
B14: 高 | C14: =COUNTIF('案例结果'!M4:M13,B14) | E14: 限制：未调用外部数据库，未进行新会话重复实验，不将 10/10 通过表述为统计准确率。
B15: 极高 | C15: =COUNTIF('案例结果'!M4:M13,B15)
B18: 工作表导航
B19: 工作表 | C19: 内容
B20: 案例结果 | C20: 逐案评分、风险等级、证据与验收
B21: 完整报告 | C21: 十个案例的八模块完整输出
B22: 过程记录 | C22: 案例内置、生成、复核和固化步骤
B23: 评分口径 | C23: 附录评分锚点与硬性规则
B24: 来源与边界 | C24: 来源、版本、日期和研究限制

Sheet 案例结果
B1: 分数为教学启发式指标；总分为公式，最终等级在硬性触发时不得低于“高”。
B2: 逐案评分与验收结果
A3: 案例 | B3: 输入文件 | C3: 预期触发点 | D3: 信息完整度 | E3: A | F3: B | G3: C | H3: D | I3: E | J3: 总分 | K3: 基础等级 | L3: 硬性触发 | M3: 最终等级 | N3: 风险展示 | O3: 关键评分证据 | P3: 人工复核 | Q3: 失败类型 | R3: 结构验收 | S3: 规则复核（自评） | T3: 运行日期 | U3: Skill 版本
A4: case_01 | B4: references/test_cases/case_01.txt | C4: A/B/C/D 高风险；E 信息不全；硬性等级不低于高 | D4: 低 | E4: 2 | F4: 2 | G4: 2 | H4: 2 | I4: 1 | J4: =SUM(E4:I4) | K4: =IF(J4<=2,"低",IF(J4<=4,"中",IF(J4<=7,"高","极高"))) | L4: 是 | M4: =IF(AND(L4="是",OR(K4="低",K4="中")),"高",K4) | N4: =IF(D4="低","信息不足；","")&M4 | O4: A 主体与背书：“国资背景、银行兜底”“转入某个人账户”；主体登记与兜底依据缺失 B 资产透明度：“未列发行人登记信息、托管机构、资金投向、费用和赎回条件”；无法穿透底层资产 C 收益风险匹配：“年化收益 18%”“保本保息、稳赚不赔”；高收益与无风险假设冲突 D 销售表达：“保本保息、稳赚不赔”；绝对化收益表达 E 流动性与条款：已披露 12 个月期限，但“费用和赎回条件”未列 | P4: 停止向个人账户转账；索取正式合同、发行与销售登记、托管和审计材料；通过权威渠道核验主体、收款授权与担保；保存宣传页和付款指令。 | Q4: 无 | R4: 通过 | S4: 通过 | T4: 2026-10-28 | U4: v0.4.0-case-calibration
A5: case_02 | B5: references/test_cases/case_02.txt | C5: 主体、资产和条款信息缺失；不得直接认定诈骗 | D5: 低 | E5: 1 | F5: 1 | G5: 1 | H5: 0 | I5: 1 | J5: =SUM(E5:I5) | K5: =IF(J5<=2,"低",IF(J5<=4,"中",IF(J5<=7,"高","极高"))) | L5: 否 | M5: =IF(AND(L5="是",OR(K5="低",K5="中")),"高",K5) | N5: =IF(D5="低","信息不足；","")&M5 | O5: A 主体与背书：“未列发行人、管理人、托管机构”；主体信息不全 B 资产透明度：“资金用于优质项目”；只有概括投向，项目和比例不明 C 收益风险匹配：“预期年化收益 5%”；收益依据与费用披露不足 D 销售表达：仅见“专业团队管理”一般宣传，未见绝对化收益或催促 E 流动性与条款：“费用和赎回条件”未列，条款不完整 | P5: 索取可下载的完整合同、发行与管理主体资料、托管证明、项目清单、费用表和赎回规则；核验“优质项目”的具体标准。 | Q5: 无 | R5: 通过 | S5: 通过 | T5: 2026-10-28 | U5: v0.4.0-case-calibration
A6: case_03 | B6: references/test_cases/case_03.txt | C6: 稀缺性催促、隐瞒真实信息；硬性等级不低于高 | D6: 低 | E6: 1 | F6: 2 | G6: 1 | H6: 2 | I6: 1 | J6: =SUM(E6:I6) | K6: =IF(J6<=2,"低",IF(J6<=4,"中",IF(J6<=7,"高","极高"))) | L6: 是 | M6: =IF(AND(L6="是",OR(K6="低",K6="中")),"高",K6) | N6: =IF(D6="低","信息不足；","")&M6 | O6: A 主体与背书：“材料未说明发行主体”；工作人员代持关系待核验 B 资产透明度：“材料未说明发行主体和资金投向”；无资金投向 C 收益风险匹配：全文未披露收益依据与费用，收益风险无法评估 D 销售表达：“不要向家人展示合同，免得他们看不懂耽误机会”；要求隐瞒并妨碍独立复核 E 流动性与条款：“内部额度，今天不转账永久失去机会”；未见期限、赎回和违约条款 | P6: 不要转账或接受代持；要求直接向家人或独立专业人士出示合同；核验发行主体、收款账户和授权；保存群聊与付款要求原文。 | Q6: 无 | R6: 通过 | S6: 通过 | T6: 2026-10-28 | U6: v0.4.0-case-calibration
A7: case_04 | B7: references/test_cases/case_04.txt | C7: 销售表述与赎回条款冲突；流动性和销售表达风险 | D7: 低 | E7: 1 | F7: 2 | G7: 1 | H7: 2 | I7: 2 | J7: =SUM(E7:I7) | K7: =IF(J7<=2,"低",IF(J7<=4,"中",IF(J7<=7,"高","极高"))) | L7: 否 | M7: =IF(AND(L7="是",OR(K7="低",K7="中")),"高",K7) | N7: =IF(D7="低","信息不足；","")&M7 | O7: A 主体与背书：所给“现金宝产品广告”与合同片段未列发行或管理主体 B 资产透明度：所附材料无资金投向，无法判断底层资产 C 收益风险匹配：“与活期存款完全相同”；未披露收益依据和完整风险假设 D 销售表达：“随时可无成本取出”与延期及 1.5% 赎回费条款冲突 E 流动性与条款：“随时可无成本取出”与“可延期办理”“支付 1.5% 费用”直接冲突 | P7: 索取完整合同和全部费用表；核对开放日、延期、巨额赎回与短期赎回费；要求销售方书面纠正“完全相同、无成本”表述。 | Q7: 无 | R7: 通过 | S7: 通过 | T7: 2026-10-28 | U7: v0.4.0-case-calibration
A8: case_05 | B8: references/test_cases/case_05.txt | C8: 专业术语不得替代披露；要求大白话解释与信息缺失清单 | D8: 低 | E8: 1 | F8: 1 | G8: 1 | H8: 1 | I8: 1 | J8: =SUM(E8:I8) | K8: =IF(J8<=2,"低",IF(J8<=4,"中",IF(J8<=7,"高","极高"))) | L8: 否 | M8: =IF(AND(L8="是",OR(K8="低",K8="中")),"高",K8) | N8: =IF(D8="低","信息不足；","")&M8 | O8: A 主体与背书：“某结构化产品说明”未列发行、管理与托管主体 B 资产透明度：“挂钩一篮子资产，采用优先劣后安排”；构成与嵌套关系不清 C 收益风险匹配：“估值方法”“最大损失”未解释，收益风险假设不足 D 销售表达：“由量化模型动态调整”等术语弱化了对实际风险的解释 E 流动性与条款：全文未列期限、赎回和费用条款 | P8: 要求销售方用大白话解释资产构成、优先劣后损失顺序、估值方法、调整频率和最大损失；索取主体、合同、费用、赎回与压力情景材料。 | Q8: 无 | R8: 通过 | S8: 通过 | T8: 2026-10-28 | U8: v0.4.0-case-calibration
A9: case_06 | B9: references/test_cases/case_06.txt | C9: 期限错配、流动性与收益风险冲突 | D9: 低 | E9: 1 | F9: 1 | G9: 2 | H9: 2 | I9: 2 | J9: =SUM(E9:I9) | K9: =IF(J9<=2,"低",IF(J9<=4,"中",IF(J9<=7,"高","极高"))) | L9: 否 | M9: =IF(AND(L9="是",OR(K9="低",K9="中")),"高",K9) | N9: =IF(D9="低","信息不足；","")&M9 | O9: A 主体与背书：“未提供退出资金来源或担保合同”；主体与支持安排待核验 B 资产透明度：“主要资金投向未上市长期项目”；方向明确但项目和退出安排不清 C 收益风险匹配：“本金不受市场波动影响”与未上市长期项目风险冲突 D 销售表达：“每周随时退出且本金不受市场波动影响”；绝对化退出和本金表述 E 流动性与条款：“封闭期为 3 年”却承诺“每周随时退出”，存在严重期限错配 | P9: 索取项目清单、估值与退出安排；核验每周退出的资金来源、封闭期例外和担保合同；要求解释后续融资未实现时的损失与延期机制。 | Q9: 无 | R9: 通过 | S9: 通过 | T9: 2026-10-28 | U9: v0.4.0-case-calibration
A10: case_07 | B10: references/test_cases/case_07.txt | C10: 不得补写评级；指出票面收益不等于实际持有收益 | D10: 低 | E10: 1 | F10: 1 | G10: 2 | H10: 2 | I10: 1 | J10: =SUM(E10:I10) | K10: =IF(J10<=2,"低",IF(J10<=4,"中",IF(J10<=7,"高","极高"))) | L10: 否 | M10: =IF(AND(L10="是",OR(K10="低",K10="中")),"高",K10) | N10: =IF(D10="低","信息不足；","")&M10 | O10: A 主体与背书：“某债券型产品材料”未列发行、管理和托管主体 B 资产透明度：仅列“所投资债券的票面利率 6%”，债券与组合细节不足 C 收益风险匹配：将“票面利率 6%”直接等同“每年稳定获得 6%”，收益逻辑不成立 D 销售表达：“每年稳定获得 6%”属于稳定绝对化收益表达 E 流动性与条款：“提前卖出安排”和产品费率未列，流动性条款不完整 | P10: 索取债券清单与信用资料、买入价格、到期收益率、费率、久期和提前卖出规则；要求补充利率风险说明并更正稳定收益宣传。 | Q10: 无 | R10: 通过 | S10: 通过 | T10: 2026-10-28 | U10: v0.4.0-case-calibration
A11: case_08 | B11: references/test_cases/case_08.txt | C11: 收益风险比较失效；不得自行补实时国债利率 | D11: 低 | E11: 1 | F11: 2 | G11: 2 | H11: 1 | I11: 1 | J11: =SUM(E11:I11) | K11: =IF(J11<=2,"低",IF(J11<=4,"中",IF(J11<=7,"高","极高"))) | L11: 否 | M11: =IF(AND(L11="是",OR(K11="低",K11="中")),"高",K11) | N11: =IF(D11="低","信息不足；","")&M11 | O11: A 主体与背书：“没有发行人信用资料、产品期限、担保合同”；主体与支持依据不全 B 资产透明度：“仅附一张收益数字海报”；无资金投向 C 收益风险匹配：“年化 12%，与国债一样安全”；高收益与安全比较逻辑冲突 D 销售表达：“与国债一样安全”属于夸大安全性的比较宣传 E 流动性与条款：“流动性安排”未披露，但未见直接赎回冲突 | P11: 索取发行人信用资料、完整合同、期限、投向、费用、流动性与担保合同；由人工选择同期限同口径基准后再比较，不自行补实时利率。 | Q11: 无 | R11: 通过 | S11: 通过 | T11: 2026-10-28 | U11: v0.4.0-case-calibration
A12: case_09 | B12: references/test_cases/case_09.txt | C12: 主体一致性和背书证明待核验；不得直接判定假冒 | D12: 低 | E12: 1 | F12: 2 | G12: 1 | H12: 1 | I12: 1 | J12: =SUM(E12:I12) | K12: =IF(J12<=2,"低",IF(J12<=4,"中",IF(J12<=7,"高","极高"))) | L12: 否 | M12: =IF(AND(L12="是",OR(K12="低",K12="中")),"高",K12) | N12: =IF(D12="低","信息不足；","")&M12 | O12: A 主体与背书：“发行人为甲公司”“收款主体为乙公司”；主体不一致且授权待核验 B 资产透明度：全文未披露资金投向，无法穿透资产 C 收益风险匹配：全文未披露收益依据与费用，收益风险无法评估 D 销售表达：“国资战略协同”反复出现，但证明缺失，存在夸大背书信号 E 流动性与条款：全文未列期限、赎回和违约条款 | P12: 暂停向乙公司付款；索取甲乙公司股权、受托或代收关系说明及授权文件；核验“国资战略协同”的具体含义；补充合同、投向、费用和赎回材料。 | Q12: 无 | R12: 通过 | S12: 通过 | T12: 2026-10-28 | U12: v0.4.0-case-calibration
A13: case_10 | B13: references/test_cases/case_10.txt | C13: 可仍有信息缺口，但不得仅因金融术语或预期收益误判为极高风险 | D13: 中 | E13: 0 | F13: 1 | G13: 0 | H13: 0 | I13: 1 | J13: =SUM(E13:I13) | K13: =IF(J13<=2,"低",IF(J13<=4,"中",IF(J13<=7,"高","极高"))) | L13: 否 | M13: =IF(AND(L13="是",OR(K13="低",K13="中")),"高",K13) | N13: =IF(D13="低","信息不足；","")&M13 | O13: A 主体与背书：“材料列明发行人、管理人、托管人”；未见可疑背书 B 资产透明度：“资金主要投向高流动性短期债务工具”，但“缺少具体资产比例” C 收益风险匹配：“披露信用、利率和流动性风险，列出管理费与托管费”；收益风险披露较匹配 D 销售表达：“历史业绩不代表未来，收益存在波动”；无绝对化收益表达 E 流动性与条款：“约定每月开放一次赎回”，但赎回费用和违约责任细节不全 | P13: 索取具体资产比例、完整赎回费用和违约责任；通过权威渠道核验主体与托管登记；保留现有风险披露作为对照样本。 | Q13: 无 | R13: 通过 | S13: 通过 | T13: 2026-10-28 | U13: v0.4.0-case-calibration

Sheet 完整报告
B1: 每份报告均包含输入摘要、风险等级、评分拆解、证据表、收益风险、信息完整度、人工复核和边界声明。
B2: 十个案例完整输出
A3: 案例 | B3: 合成输入 | C3: 完整体检报告 | D3: 输出字符数
A4: case_01 | B4: 某财富管理有限公司推出“鑫安 6 号”，期限 12 个月，宣传年化收益 18%，承诺保本保息、稳赚不赔。销售人员称产品有国资背景、银行兜底，但页面未列发行人登记信息、托管机构、资金投向、费用和赎回条件，并要求投资者将认购款转入某个人账户。 | C4: 【输入摘要】已披露：产品名“鑫安 6 号”、期限 12 个月、宣传年化收益 18%；披露不足：财富管理主体、国资背景与银行兜底均只有宣传表述，证明待核验；信息缺失：发行人登记、销售授权、托管、资金投向、费用、赎回、担保合同、审计与信用评级。 【风险等级】信息不足；极高；教学评分 9/10；硬性触发：是。本结论仅针对教学合成文本。 【评分拆解】 A 主体与背书：2 分｜“国资背景、银行兜底”“转入某个人账户”；主体登记与兜底依据缺失 B 资产透明度：2 分｜“未列发行人登记信息、托管机构、资金投向、费用和赎回条件”；无法穿透底层资产 C 收益风险匹配：2 分｜“年化收益 18%”“保本保息、稳赚不赔”；高收益与无风险假设冲突 D 销售表达：2 分｜“保本保息、稳赚不赔”；绝对化收益表达 E 流动性与条款：1 分｜已披露 12 个月期限，但“费用和赎回条件”未列 【风险证据表】 原文｜触发规则｜课程机制｜置信限制 年化收益 18%｜高收益须结合风险与基准分析｜风险收益匹配｜无可靠基准，不能判断收益是否合理 保本保息、稳赚不赔｜绝对化收益；硬性触发｜风险揭示与信息不对称｜只识别文本信号，不作违法认定 国资背景、银行兜底｜主体与担保背书待核验｜信用支持与信息生产｜未核验真伪，不补写担保事实 转入某个人账户｜个人账户收款；硬性触发｜资金流与受托责任｜立即停止转账并人工核验收款授权 【收益风险分析】18% 只是宣传值；缺少同期限、同信用、同流动性、同税负基准，无法比较。保本保息与稳赚不赔排除了正常风险承担，和未披露底层资产、担保合同的状态不相容。 【信息完整度】低 已披露：产品名“鑫安 6 号”、期限 12 个月、宣传年化收益 18% 披露不足：财富管理主体、国资背景与银行兜底均只有宣传表述，证明待核验 未披露：发行人登记、销售授权、托管、资金投向、费用、赎回、担保合同、审计与信用评级 【人工复核清单】停止向个人账户转账；索取正式合同、发行与销售登记、托管和审计材料；通过权威渠道核验主体、收款授权与担保；保存宣传页和付款指令。 【边界声明】本报告仅基于所给教学合成文本进行风险提示，不构成投资、法律或信用结论；未进行工商、司法、监管或其他外部数据库核验，教学评分不是违约概率。 | D4: =LEN(C4)
A5: case_02 | B5: 安盈 3 号投资页面写明产品期限 6 个月、预期年化收益 5%，资金用于优质项目。页面同时展示“专业团队管理”的宣传语，但未列发行人、管理人、托管机构、具体投向、费用和赎回条件，也未提供合同下载入口。 | C5: 【输入摘要】已披露：产品名“安盈 3 号”、期限 6 个月、预期年化收益 5%；披露不足：资金仅概括为“优质项目”，团队能力仅有一般宣传；信息缺失：发行人、管理人、托管机构、具体投向、费用、赎回条件与合同下载入口。 【风险等级】信息不足；中；教学评分 4/10；硬性触发：否。本结论仅针对教学合成文本。 【评分拆解】 A 主体与背书：1 分｜“未列发行人、管理人、托管机构”；主体信息不全 B 资产透明度：1 分｜“资金用于优质项目”；只有概括投向，项目和比例不明 C 收益风险匹配：1 分｜“预期年化收益 5%”；收益依据与费用披露不足 D 销售表达：0 分｜仅见“专业团队管理”一般宣传，未见绝对化收益或催促 E 流动性与条款：1 分｜“费用和赎回条件”未列，条款不完整 【风险证据表】 原文｜触发规则｜课程机制｜置信限制 专业团队管理｜一般宣传不能替代主体与授权披露｜信息生产与披露｜不能据此推断团队资质 资金用于优质项目｜投向概括且“优质”缺少标准｜资产穿透与风险定价｜不直接认定诈骗，需补充项目清单 未提供合同下载入口｜关键条款不可得｜信息不对称｜仅说明本轮材料不完整 【收益风险分析】5% 为预期值而非承诺收益；缺少信用、期限、流动性、税负和估值基准，无法比较。不得仅因信息缺失认定诈骗，但也不能把“优质项目”当作低风险证明。 【信息完整度】低 已披露：产品名“安盈 3 号”、期限 6 个月、预期年化收益 5% 披露不足：资金仅概括为“优质项目”，团队能力仅有一般宣传 未披露：发行人、管理人、托管机构、具体投向、费用、赎回条件与合同下载入口 【人工复核清单】索取可下载的完整合同、发行与管理主体资料、托管证明、项目清单、费用表和赎回规则；核验“优质项目”的具体标准。 【边界声明】本报告仅基于所给教学合成文本进行风险提示，不构成投资、法律或信用结论；未进行工商、司法、监管或其他外部数据库核验，教学评分不是违约概率。 | D5: =LEN(C5)
A6: case_03 | B6: 恒信 1 号仅在群聊中销售，对方称“内部额度，今天不转账永久失去机会”，要求认购款由工作人员代持，并特别强调“不要向家人展示合同，免得他们看不懂耽误机会”。材料未说明发行主体和资金投向。 | C6: 【输入摘要】已披露：产品名“恒信 1 号”，销售渠道为群聊；披露不足：工作人员代持安排的资金流与法律关系不清；信息缺失：发行主体、资金投向、收益依据、费用、期限、赎回、合同与授权材料。 【风险等级】信息不足；高；教学评分 7/10；硬性触发：是。本结论仅针对教学合成文本。 【评分拆解】 A 主体与背书：1 分｜“材料未说明发行主体”；工作人员代持关系待核验 B 资产透明度：2 分｜“材料未说明发行主体和资金投向”；无资金投向 C 收益风险匹配：1 分｜全文未披露收益依据与费用，收益风险无法评估 D 销售表达：2 分｜“不要向家人展示合同，免得他们看不懂耽误机会”；要求隐瞒并妨碍独立复核 E 流动性与条款：1 分｜“内部额度，今天不转账永久失去机会”；未见期限、赎回和违约条款 【风险证据表】 原文｜触发规则｜课程机制｜置信限制 内部额度，今天不转账永久失去机会｜稀缺性营销与转账催促｜行为偏差与信息不对称｜催促本身不等于违法，但应暂停付款 要求认购款由工作人员代持｜资金控制权和授权不清｜委托代理与资金流｜未提供代持协议，不推断资金去向 不要向家人展示合同，免得他们看不懂耽误机会｜要求隐瞒真实信息；硬性触发｜信息透明与独立决策｜明确阻碍第三方复核 【收益风险分析】没有收益、信用、期限、流动性、税负或估值信息，无法比较。主要风险来自信息被刻意限制、付款催促和代持安排，而非任何假定的收益率。 【信息完整度】低 已披露：产品名“恒信 1 号”，销售渠道为群聊 披露不足：工作人员代持安排的资金流与法律关系不清 未披露：发行主体、资金投向、收益依据、费用、期限、赎回、合同与授权材料 【人工复核清单】不要转账或接受代持；要求直接向家人或独立专业人士出示合同；核验发行主体、收款账户和授权；保存群聊与付款要求原文。 【边界声明】本报告仅基于所给教学合成文本进行风险提示，不构成投资、法律或信用结论；未进行工商、司法、监管或其他外部数据库核验，教学评分不是违约概率。 | D6: =LEN(C6)
A7: case_04 | B7: 现金宝产品广告声称“与活期存款完全相同、随时可无成本取出”。所附合同片段却规定：单个开放日净赎回超过上期份额 10% 时可延期办理，持有不足 30 日赎回需支付 1.5% 费用。 | C7: 【输入摘要】已披露：产品名“现金宝”；开放日延期阈值为上期份额 10%；持有不足 30 日赎回费 1.5%；披露不足：广告与合同片段均已提供，但产品全貌不完整；信息缺失：发行与管理主体、资金投向、收益、其他费用、完整赎回和违约责任。 【风险等级】信息不足；极高；教学评分 8/10；硬性触发：否。本结论仅针对教学合成文本。 【评分拆解】 A 主体与背书：1 分｜所给“现金宝产品广告”与合同片段未列发行或管理主体 B 资产透明度：2 分｜所附材料无资金投向，无法判断底层资产 C 收益风险匹配：1 分｜“与活期存款完全相同”；未披露收益依据和完整风险假设 D 销售表达：2 分｜“随时可无成本取出”与延期及 1.5% 赎回费条款冲突 E 流动性与条款：2 分｜“随时可无成本取出”与“可延期办理”“支付 1.5% 费用”直接冲突 【风险证据表】 原文｜触发规则｜课程机制｜置信限制 与活期存款完全相同、随时可无成本取出｜绝对化流动性和成本表述｜流动性风险与信息披露｜需以合同为准，不把广告等同存款保险 单个开放日净赎回超过上期份额 10% 时可延期办理｜存在延期赎回限制｜流动性分层与赎回约束｜未提供完整合同，其他限制未知 持有不足 30 日赎回需支付 1.5% 费用｜赎回并非无成本｜费用与流动性定价｜仅按所给条款计算，不推断其他费用 【收益风险分析】广告的“随时、无成本”与合同延期和收费安排冲突，导致流动性与税负/费用比较口径失效；缺少收益与底层资产信息，无法作数值收益比较。 【信息完整度】低 已披露：产品名“现金宝”；开放日延期阈值为上期份额 10%；持有不足 30 日赎回费 1.5% 披露不足：广告与合同片段均已提供，但产品全貌不完整 未披露：发行与管理主体、资金投向、收益、其他费用、完整赎回和违约责任 【人工复核清单】索取完整合同和全部费用表；核对开放日、延期、巨额赎回与短期赎回费；要求销售方书面纠正“完全相同、无成本”表述。 【边界声明】本报告仅基于所给教学合成文本进行风险提示，不构成投资、法律或信用结论；未进行工商、司法、监管或其他外部数据库核验，教学评分不是违约概率。 | D7: =LEN(C7)
A8: case_05 | B8: 某结构化产品说明仅写“挂钩一篮子资产，采用优先劣后安排，由量化模型动态调整”。材料未解释一篮子资产的构成、优先与劣后的损失承担顺序、估值方法、调整频率和投资者可能承担的最大损失。 | C8: 【输入摘要】已披露：产品为结构化产品，采用挂钩资产、优先劣后和量化模型动态调整；披露不足：结构术语有披露，但无法转化为可理解的损失与现金流规则；信息缺失：主体、资产构成、损失承担顺序、估值方法、调整频率、最大损失、收益、费用与赎回。 【风险等级】信息不足；高；教学评分 5/10；硬性触发：否。本结论仅针对教学合成文本。 【评分拆解】 A 主体与背书：1 分｜“某结构化产品说明”未列发行、管理与托管主体 B 资产透明度：1 分｜“挂钩一篮子资产，采用优先劣后安排”；构成与嵌套关系不清 C 收益风险匹配：1 分｜“估值方法”“最大损失”未解释，收益风险假设不足 D 销售表达：1 分｜“由量化模型动态调整”等术语弱化了对实际风险的解释 E 流动性与条款：1 分｜全文未列期限、赎回和费用条款 【风险证据表】 原文｜触发规则｜课程机制｜置信限制 挂钩一篮子资产｜资产构成未披露｜资产穿透与估值｜术语不能证明分散或低风险 采用优先劣后安排｜损失承担顺序未披露｜结构化信用风险｜无法判断投资者所处层级 由量化模型动态调整｜调整频率、估值和最大损失未知｜模型风险与信息生产｜不得把模型表述当作收益保证 【收益风险分析】缺少信用、期限、流动性、税负和估值假设，无法比较。应先用大白话解释“买什么、谁先亏、如何估值、多久调整、最多亏多少”，再讨论收益风险。 【信息完整度】低 已披露：产品为结构化产品，采用挂钩资产、优先劣后和量化模型动态调整 披露不足：结构术语有披露，但无法转化为可理解的损失与现金流规则 未披露：主体、资产构成、损失承担顺序、估值方法、调整频率、最大损失、收益、费用与赎回 【人工复核清单】要求销售方用大白话解释资产构成、优先劣后损失顺序、估值方法、调整频率和最大损失；索取主体、合同、费用、赎回与压力情景材料。 【边界声明】本报告仅基于所给教学合成文本进行风险提示，不构成投资、法律或信用结论；未进行工商、司法、监管或其他外部数据库核验，教学评分不是违约概率。 | D8: =LEN(C8)
A9: case_06 | B9: 某封闭期为 3 年的产品将主要资金投向未上市长期项目，项目退出时间视后续融资安排确定。销售页面同时承诺“每周随时退出且本金不受市场波动影响”，未提供退出资金来源或担保合同。 | C9: 【输入摘要】已披露：封闭期 3 年；主要投向未上市长期项目；退出依赖后续融资；披露不足：项目方向已披露，但具体资产、退出资金来源与担保安排不清；信息缺失：主体、项目清单、估值、收益依据、费用、退出资金来源与担保合同。 【风险等级】信息不足；极高；教学评分 8/10；硬性触发：否。本结论仅针对教学合成文本。 【评分拆解】 A 主体与背书：1 分｜“未提供退出资金来源或担保合同”；主体与支持安排待核验 B 资产透明度：1 分｜“主要资金投向未上市长期项目”；方向明确但项目和退出安排不清 C 收益风险匹配：2 分｜“本金不受市场波动影响”与未上市长期项目风险冲突 D 销售表达：2 分｜“每周随时退出且本金不受市场波动影响”；绝对化退出和本金表述 E 流动性与条款：2 分｜“封闭期为 3 年”却承诺“每周随时退出”，存在严重期限错配 【风险证据表】 原文｜触发规则｜课程机制｜置信限制 封闭期为 3 年｜产品资金锁定期较长｜期限结构｜需与资产退出期限联合判断 项目退出时间视后续融资安排确定｜退出来源不确定｜流动性与再融资风险｜后续融资并非已落实事实 每周随时退出且本金不受市场波动影响｜销售承诺与资产条款冲突｜期限错配与风险揭示｜未见担保合同，不能认定存在有效担保 【收益风险分析】未上市长期项目的退出时间不确定，而销售端承诺每周退出，形成明显期限错配。缺少同信用、同流动性基准与估值信息，无法比较；本金不受波动影响的说法没有担保合同支持。 【信息完整度】低 已披露：封闭期 3 年；主要投向未上市长期项目；退出依赖后续融资 披露不足：项目方向已披露，但具体资产、退出资金来源与担保安排不清 未披露：主体、项目清单、估值、收益依据、费用、退出资金来源与担保合同 【人工复核清单】索取项目清单、估值与退出安排；核验每周退出的资金来源、封闭期例外和担保合同；要求解释后续融资未实现时的损失与延期机制。 【边界声明】本报告仅基于所给教学合成文本进行风险提示，不构成投资、法律或信用结论；未进行工商、司法、监管或其他外部数据库核验，教学评分不是违约概率。 | D9: =LEN(C9)
A10: case_07 | B10: 某债券型产品材料列出所投资债券的票面利率 6%，并据此宣传“每年稳定获得 6%”。材料未列债券信用等级、买入价格、到期收益率、产品费率、久期、提前卖出安排和利率风险说明。 | C10: 【输入摘要】已披露：债券型产品；所投资债券票面利率 6%；披露不足：仅披露债券类型和票面利率，实际持有收益所需参数不足；信息缺失：主体、信用等级、买入价格、到期收益率、费率、久期、提前卖出与利率风险说明。 【风险等级】信息不足；高；教学评分 7/10；硬性触发：否。本结论仅针对教学合成文本。 【评分拆解】 A 主体与背书：1 分｜“某债券型产品材料”未列发行、管理和托管主体 B 资产透明度：1 分｜仅列“所投资债券的票面利率 6%”，债券与组合细节不足 C 收益风险匹配：2 分｜将“票面利率 6%”直接等同“每年稳定获得 6%”，收益逻辑不成立 D 销售表达：2 分｜“每年稳定获得 6%”属于稳定绝对化收益表达 E 流动性与条款：1 分｜“提前卖出安排”和产品费率未列，流动性条款不完整 【风险证据表】 原文｜触发规则｜课程机制｜置信限制 票面利率 6%｜票面利率不等于实际持有收益｜债券定价与到期收益率｜信用等级缺失，待人工核验，不得补写 每年稳定获得 6%｜把票面利率宣传为稳定产品收益｜利率风险与费用侵蚀｜未考虑买入价格、费率、久期和出售价格 材料未列债券信用等级、买入价格、到期收益率、产品费率、久期、提前卖出安排和利率风险说明｜关键收益风险参数缺失｜信用与利率风险定价｜信息缺口不等于已证实高风险 【收益风险分析】票面利率不等于实际持有收益。实际结果还取决于买入价格、到期收益率、信用风险、产品费率、久期和提前卖出价格；这些参数均缺失，因此无法比较，也不补写任何信用评级。 【信息完整度】低 已披露：债券型产品；所投资债券票面利率 6% 披露不足：仅披露债券类型和票面利率，实际持有收益所需参数不足 未披露：主体、信用等级、买入价格、到期收益率、费率、久期、提前卖出与利率风险说明 【人工复核清单】索取债券清单与信用资料、买入价格、到期收益率、费率、久期和提前卖出规则；要求补充利率风险说明并更正稳定收益宣传。 【边界声明】本报告仅基于所给教学合成文本进行风险提示，不构成投资、法律或信用结论；未进行工商、司法、监管或其他外部数据库核验，教学评分不是违约概率。 | D10: =LEN(C10)
A11: case_08 | B11: 某产品宣传“年化 12%，与国债一样安全”，仅附一张收益数字海报，没有发行人信用资料、产品期限、担保合同、流动性安排或同期限国债比较口径。 | C11: 【输入摘要】已披露：宣传年化 12%，并声称“与国债一样安全”；披露不足：只有收益数字海报，安全比较缺少同期限与信用口径；信息缺失：发行人信用、资金投向、期限、担保合同、流动性、费用与同期限国债比较口径。 【风险等级】信息不足；高；教学评分 7/10；硬性触发：否。本结论仅针对教学合成文本。 【评分拆解】 A 主体与背书：1 分｜“没有发行人信用资料、产品期限、担保合同”；主体与支持依据不全 B 资产透明度：2 分｜“仅附一张收益数字海报”；无资金投向 C 收益风险匹配：2 分｜“年化 12%，与国债一样安全”；高收益与安全比较逻辑冲突 D 销售表达：1 分｜“与国债一样安全”属于夸大安全性的比较宣传 E 流动性与条款：1 分｜“流动性安排”未披露，但未见直接赎回冲突 【风险证据表】 原文｜触发规则｜课程机制｜置信限制 年化 12%，与国债一样安全｜收益与安全比较口径失效｜信用风险与风险溢价｜未使用实时国债利率，不补写外部数据 仅附一张收益数字海报｜缺少合同和资产证据｜信息生产与披露｜海报不能证明收益或担保 没有发行人信用资料、产品期限、担保合同、流动性安排或同期限国债比较口径｜同期限同信用比较不可行｜期限与信用定价｜无法比较，不作数值结论 【收益风险分析】缺少同期限、同信用、同流动性、同税负口径，无法比较；本轮未使用实时国债利率。12% 与“一样安全”的组合需要发行人信用和担保合同支持，而材料均未提供。 【信息完整度】低 已披露：宣传年化 12%，并声称“与国债一样安全” 披露不足：只有收益数字海报，安全比较缺少同期限与信用口径 未披露：发行人信用、资金投向、期限、担保合同、流动性、费用与同期限国债比较口径 【人工复核清单】索取发行人信用资料、完整合同、期限、投向、费用、流动性与担保合同；由人工选择同期限同口径基准后再比较，不自行补实时利率。 【边界声明】本报告仅基于所给教学合成文本进行风险提示，不构成投资、法律或信用结论；未进行工商、司法、监管或其他外部数据库核验，教学评分不是违约概率。 | D11: =LEN(C11)
A12: case_09 | B12: 某产品宣传页反复使用“国资战略协同”字样，但合同中的发行人为甲公司，付款通知中的收款主体为乙公司。材料没有说明甲乙公司的股权、受托或代收关系，也没有提供授权文件。 | C12: 【输入摘要】已披露：宣传使用“国资战略协同”；合同发行人为甲公司；付款收款主体为乙公司；披露不足：甲乙公司关系、国资协同含义与代收授权均未说明；信息缺失：股权/受托/代收关系、授权文件、资金投向、收益、费用、期限和赎回。 【风险等级】信息不足；高；教学评分 6/10；硬性触发：否。本结论仅针对教学合成文本。 【评分拆解】 A 主体与背书：1 分｜“发行人为甲公司”“收款主体为乙公司”；主体不一致且授权待核验 B 资产透明度：2 分｜全文未披露资金投向，无法穿透资产 C 收益风险匹配：1 分｜全文未披露收益依据与费用，收益风险无法评估 D 销售表达：1 分｜“国资战略协同”反复出现，但证明缺失，存在夸大背书信号 E 流动性与条款：1 分｜全文未列期限、赎回和违约条款 【风险证据表】 原文｜触发规则｜课程机制｜置信限制 国资战略协同｜背书含义和证明待核验｜信息不对称与信用支持｜不将宣传等同于国有担保 合同中的发行人为甲公司，付款通知中的收款主体为乙公司｜合同与付款主体不一致｜委托代理与资金流｜不得直接判定假冒，需核验代收关系 没有提供授权文件｜受托或代收授权缺失｜授权与利益冲突｜未核验前不补写股权关系 【收益风险分析】收益、信用、期限、流动性、税负和估值假设均不足，无法比较。核心问题是发行、收款与宣传背书是否一致；不得直接判定假冒，应先核验股权、受托或代收关系。 【信息完整度】低 已披露：宣传使用“国资战略协同”；合同发行人为甲公司；付款收款主体为乙公司 披露不足：甲乙公司关系、国资协同含义与代收授权均未说明 未披露：股权/受托/代收关系、授权文件、资金投向、收益、费用、期限和赎回 【人工复核清单】暂停向乙公司付款；索取甲乙公司股权、受托或代收关系说明及授权文件；核验“国资战略协同”的具体含义；补充合同、投向、费用和赎回材料。 【边界声明】本报告仅基于所给教学合成文本进行风险提示，不构成投资、法律或信用结论；未进行工商、司法、监管或其他外部数据库核验，教学评分不是违约概率。 | D12: =LEN(C12)
A13: case_10 | B13: 安诚 1 号为教学合成的对照产品。材料列明发行人、管理人、托管人和 1 年期限，说明资金主要投向高流动性短期债务工具，披露信用、利率和流动性风险，列出管理费与托管费，约定每月开放一次赎回，并明确“历史业绩不代表未来，收益存在波动”。材料未承诺保本，但缺少具体资产比例。 | C13: 【输入摘要】已披露：发行人、管理人、托管人、1 年期限、短期债务工具投向、信用/利率/流动性风险、管理费与托管费、每月开放赎回；披露不足：具体资产比例、赎回费用与违约责任未明确；信息缺失：具体资产比例、部分赎回费用与违约责任细节。 【风险等级】低；教学评分 2/10；硬性触发：否。本结论仅针对教学合成文本。 【评分拆解】 A 主体与背书：0 分｜“材料列明发行人、管理人、托管人”；未见可疑背书 B 资产透明度：1 分｜“资金主要投向高流动性短期债务工具”，但“缺少具体资产比例” C 收益风险匹配：0 分｜“披露信用、利率和流动性风险，列出管理费与托管费”；收益风险披露较匹配 D 销售表达：0 分｜“历史业绩不代表未来，收益存在波动”；无绝对化收益表达 E 流动性与条款：1 分｜“约定每月开放一次赎回”，但赎回费用和违约责任细节不全 【风险证据表】 原文｜触发规则｜课程机制｜置信限制 材料列明发行人、管理人、托管人｜主体与托管披露较清楚｜信息生产与受托责任｜登记真实性仍需外部人工核验 披露信用、利率和流动性风险｜主要风险已揭示｜风险定价｜不代表没有风险 历史业绩不代表未来，收益存在波动｜非绝对化收益表达｜风险揭示｜不得仅因金融术语或预期收益误判 缺少具体资产比例｜资产透明度仍有缺口｜资产穿透｜信息缺口单独列示，不等同违法 【收益风险分析】已披露信用、利率和流动性风险，未提供收益数值或可靠外部基准，无法比较。剩余缺口主要是资产比例和部分条款细节；不得仅因金融术语或预期收益将其判为极高风险。 【信息完整度】中 已披露：发行人、管理人、托管人、1 年期限、短期债务工具投向、信用/利率/流动性风险、管理费与托管费、每月开放赎回 披露不足：具体资产比例、赎回费用与违约责任未明确 未披露：具体资产比例、部分赎回费用与违约责任细节 【人工复核清单】索取具体资产比例、完整赎回费用和违约责任；通过权威渠道核验主体与托管登记；保留现有风险披露作为对照样本。 【边界声明】本报告仅基于所给教学合成文本进行风险提示，不构成投资、法律或信用结论；未进行工商、司法、监管或其他外部数据库核验，教学评分不是违约概率。 | D13: =LEN(C13)

Sheet 过程记录
B1: 按“输入与答案分离—单案生成—输出后复核—结果固化”执行。
B2: 案例校准过程记录
A3: 步骤 | B3: 操作 | C3: 输入 | D3: 输出/证据 | E3: 结果 | F3: 日期 | G3: 限制
A4: 1 | B4: 提取附录 C 并核对案例 | C4: 提交文档 3 附录 C | D4: 10 个合成输入与 1 份预期触发点 | E4: 完成 | F4: 2026-10-28 | G4: 全部为教学合成文本
A5: 2 | B5: 加入 Skill 校准集 | C5: case_01—case_10 | D5: references/test_cases/ 与 expected_triggers.md | E5: 完成 | F5: 2026-10-28 | G5: 输入与人工答案分开存放
A6: 3 | B6: 更新校准工作流 | C6: 原 SKILL.md | D6: 新增第六部分；原六步分析顺序不变 | E6: 完成 | F6: 2026-10-28 | G6: 案例校准不修改模型权重
A7: 4 | B7: 逐案生成体检报告 | C7: 每次仅一个案例文本 | D7: 10 份八模块完整报告 | E7: 完成 | F7: 2026-10-28 | G7: 同会话生成，不是独立盲测
A8: 5 | B8: 静态结构验收 | C8: 10 份完整报告 | D8: 八模块、五维评分、边界声明检查 | E8: 10/10 通过 | F8: 2026-10-28 | G8: 仅证明结构完整
A9: 6 | B9: 输出后规则复核 | C9: 预期触发点与完整报告 | D9: 关键证据、硬性触发、对照案例检查 | E9: 10/10 通过（自评） | F9: 2026-10-28 | G9: 不等同统计准确率
A10: 7 | B10: 固化过程和结果 | C10: 评分、证据、报告和过程 | D10: financial-mirror-calibration-results.xlsx | E10: 完成 | F10: 2026-10-28 | G10: 后续需新会话重复测试

Sheet 评分口径
B1: 以下锚点来自提交文档 3 的评分表；评分不是违约概率。
B2: 教学评分口径与硬性规则
A3: 维度 | B3: 0 分 | C3: 1 分 | D3: 2 分 | E3: 本轮应用说明
A4: A 主体与背书 | B4: 主体和授权清楚且无可疑背书 | C4: 主体不全或背书待核验 | D4: 个人付款、明显假冒或绝对化兜底 | E4: 主体不一致但未证伪时取 1，不直接判假冒
A5: B 资产透明度 | B5: 投向、比例和限制较清楚 | C5: 概括投向或嵌套不清 | D5: 无投向或用途明显矛盾 | E5: 专业术语不能替代资产披露
A6: C 收益风险匹配 | B6: 收益与风险、期限和假设匹配 | C6: 收益依据或费用不足 | D6: 高收益无风险或收益逻辑矛盾 | E6: 无可靠基准时写无法比较
A7: D 销售表达 | B7: 无绝对化收益或误导催促 | C7: 夸大、稀缺营销或弱化风险 | D7: 保本稳赚或隐瞒重大限制 | E7: 保存原文，不因术语本身扣分
A8: E 流动性与条款 | B8: 期限、赎回和违约责任较清楚 | C8: 赎回或费用不完整 | D8: 赎回表述冲突或严重期限错配 | E8: 广告与合同冲突需同时引用
A11: 总分 | B11: 基础等级 | C11: 硬性规则 | D11: 信息完整度 | E11: 解释边界
A12: 0—2 | B12: 低 | C12: 个人账户收款、明确保本保息且无风险、要求隐瞒真实信息时最终等级不低于高 | D12: 高/中/低单独报告 | E12: 不作投资、法律或信用结论
A13: 3—4 | B13: 中 | C13: 同上 | D13: 信息不足不等于违法 | E13: 不作真实违约概率预测
A14: 5—7 | B14: 高 | C14: 同上 | D14: 缺失与已证实风险分开 | E14: 外部事实待人工核验
A15: 8—10 | B15: 极高 | C15: 同上 | D15: 对照案例仍有缺口但不误判 | E15: 教学评分仅用于排序

Sheet 来源与边界
B1: 本工作簿不使用外部实时金融数据，所有案例均为用户文档中的教学合成文本。
B2: 来源、版本与验收边界
A3: 项目 | B3: 内容 | C3: 定位/路径 | D3: 说明
A4: 来源名称 | B4: 提交文档3_项目原型与复现说明_金融照妖镜.docx | C4: C:\Users\songfei\Documents\kimi\tasks\2026-10-28\14-08-58-2c504b75\appendix-source.docx | D4: 附录 C：10 个教学合成测试案例
A5: Skill 名称 | B5: financial-mirror | C5: C:\Users\songfei\Documents\kimi\tasks\2026-10-28\14-08-58-2c504b75\financial-mirror | D5: 原附录 A 六步工作流保持不变
A6: Skill 版本 | B6: v0.4.0-case-calibration | C6: C:\Users\songfei\Documents\kimi\tasks\2026-10-28\14-08-58-2c504b75\financial-mirror\SKILL.md | D6: 新增教学案例校准部分
A7: 运行日期 | B7: 2026-10-28 | C7: 本地工作区 | D7: 使用当前任务时间锚点
A8: 训练含义 | B8: 案例校准与回归测试 | C8: 不修改模型参数或权重 | D8: 不得表述为模型微调
A9: 验收性质 | B9: 同会话静态结构检查与输出后规则自评 | C9: 10/10 通过 | D9: 不是独立盲测或统计准确率
A10: 外部核验 | B10: 未执行 | C10: 无工商、司法、监管或实时行情调用 | D10: 外部事实均标记待人工核验
A11: 隐私 | B11: 不含真实个人信息 | C11: 所有案例均为合成文本 | D11: 不得映射真实机构或产品
